{
  "subtitle": "Daftar istilah", 
  "description": "Daftar istilah\r\n", 
  "language": "ind_ID", 
  "title": "Daftar istilah", 
  "primary_category": "778dd03fef304a81852d302d1e83e314", 
  "created_at": "2015-01-08T02:35:43.130997+00:00", 
  "featured_in_category": false, 
  "modified_at": "2015-01-08T02:35:43.131177+00:00", 
  "_version": {
    "package_version": "0.3.1", 
    "language_version": "2.7.6", 
    "language_version_string": "2.7.6 (default, Mar 22 2014, 23:03:41) \n[GCC 4.8.2]", 
    "language": "python", 
    "package": "elastic-git"
  }, 
  "linked_pages": [], 
  "id": null, 
  "content": "**Perlindungan Anak Daftar istilah**\r\n\t\r\n**ACTs:** Artemisinin-based Combination Therapies, jenis obat yang digunakan untuk\r\nmengobati malaria Plasmodium falciparum, yaitu salah satu jenis penyakit malaria yang\r\npaling berbahaya yang dapat menyebabkan kematian terbesar.\r\n\r\n**AKB:** Angka Kematian Bayi.\r\n\r\n**AKI:** Angka Kematian Ibu.\r\n\r\n**ANC:** Ante Natal Care, Perawatan Kehamilan.\r\n\r\n**AIDS:** Acquired Immuno Deficiency Syndrome.\r\n\r\n**APD:** Alat Pelindung Diri.\r\n\r\n**ART:** Anti Retroviral Therapy \u2013satu jenis kelompok obat bagi mereka yang terinfeksi HIV\r\nkepada ibu yang positif tertular HIV.\r\nAnemia/Anaemia: Kurang darah yang dapat mengakibatkan buruknya tingkat\r\nkesehatan seseorang. Biasanya anemia disebabkan oleh kurangnya zat besi dalam menu\r\nmakanan yang dikonsumsi.\r\n\r\n**BAB:** Buang Air Besar.\r\n\r\n**BB:** Berat Badan.\r\n\r\n**BBLR:** Berat Bayi Lahir Rendah.\r\n\r\n**BCG:** Bacillus Calmette-Guerin \u2013 vaksin anti tuberculosis.\r\n\r\n**BPS:** Biro Pusat Statistik.\r\n\r\n**CEDAW:** Convention on the Elimination of All Forms of Discrimination Against Women\r\n(Konvensi mengenai Penghapusan Segala Bentuk Diskriminasi Terhadap Wanita).\r\n\r\n**DTP or DPT:** Diphtheria, Tetanus Toxoid dan Pertussis, jenis vaksin untuk batuk rejan.\r\n\r\n**DBD:** Demam Berdarah Dengue.\r\n\r\n**Eklampsia:** Satu jenis penyakit yang terjadi pada saat kehamilan tua, disertai dengan\r\ntekanan darah tinggi dan dapat mengakibatkan kekejangan terkadang diikuti dengan\r\ntidak sadar (coma).\r\n\r\n**Gondok:** Sebuah pembesaran kelenjar tiroid,yang dapat menyebabkan pembengkakan\r\nleher. Ini merupakan gejala kekurangan yodium dalam makanan yang dikonsumsi\r\nsehari-hari.\r\n\r\n**HepB:** Vaksin Hepatitis B.\r\n\r\n**Hib:** Vaksin Haemophilus Influenzae type B.\r\n\r\n**HIV:** Human Immuno Deficiency Virus.\r\n\r\n**IMS:** Infeksi Menular Seksual.\r\n\r\n**ISPA:** Infeksi Saluran Pernafasan Akut.\r\n\r\n**KB:** Keluarga Berencana.\r\n\r\n**KIA:** Kesehatan Ibu dan Anak. \r\n\r\n**KMS:** Kartu Menuju Sehat.\r\n\r\n**KPAI:** Komisi Perlindungan Anak Indonesia.\r\n\r\n**KTS:** Konseling dan Tes HIV Sukarela.\r\n\r\n**LANSIA:** Lanjut Usia.\r\n\r\n**LSM:** Lembaga Swadaya Masyarakat.\r\n\r\n**3M:** Menguras, Menutup dan Mengubur.\r\n\r\n**NAPZA:** Narkotika Psikotropika dan Zat Adiktif.\r\n\r\n**ODHA:** Orang Dengan HIV AIDS.\r\n\r\n**ORS:** Oral Rehydration Salts.\r\n\r\n**PCP Pneumonia:** Pneumo Cystis Pneumonia \u2013 infeksi yang biasa terjadi pada anak-anak dan\r\nODHA.\r\n\r\n**Pentavalent Vaccine:** Satu jenis vaksin yang mengkombinasikan vaksin DPT, HepB dan Hib.\r\nPlasmodium Falciparum Malaria: Jenis penyakit malaria yang berbahaya, yang dapat mengaki-\r\nbatkan kematian.\r\n\r\n**PMTCT:** Prevention of Mother-To-Child Transmission of HIV (Pencegahan penularan HIV dari Ibu\r\nkepada anak).\r\n\r\n**Prolonged Labour:** Buruh yang jam kerjanya lebih dari 24 jam.\r\n\r\n**PPOK:** Penyakit Paru Obstruksi Kronik .\r\n\r\n**Puskesmas:** Pusat Kesehatan Masyarakat.\r\n\r\n**3R:** Reduce, Reuse, Recycle (Mengurangi, Memanfaatkan kembali, Mendaur ulang).\r\n\r\n**RSIA:** Rumah Sakit Ibu dan Anak.\r\n\r\n**RSU:** Rumah Sakit Umum.\r\n\r\n**RSUD:** Rumah Sakit Umum Daerah.\r\n\r\n**PWS:** Pemantauan Wilayah Setempat.\r\n\r\n**SDKI:** Survey Demografi dan Kesehatan Indonesia.\r\n\r\n**SKRT:** Survey Kesehatan Rumah Tangga.\r\n\r\n**STI:** Sexually Transmitted Infection,( Infeksi yang ditularkan melalui hubungan seksual).\r\n\r\n**Stigma:** Cap buruk.\r\n\r\n**Stillbirth:** Bayi lahir mati.\r\n\r\n**TT:** Tetanus Toxoid.\r\n\r\n**UXO:** Sisa-sisa peralatan perang yang belum meledak yang telah digunakan oleh IDF (Israeli Defence\r\nForces) dalam perang 34 hari tahun 2006 di Lebanon. UXO dapat berupa serpihan bom cluster,\r\nproyektil artileri maupun roket.", 
  "source": null, 
  "featured": false, 
  "author_tags": [], 
  "image": null, 
  "published": null, 
  "position": 0, 
  "image_host": "http://thumbor.unicore.io", 
  "slug": "daftar-istilah", 
  "uuid": "b4d868d73352494f9d09f21bd61cf13a"
}