{
  "subtitle": "Pencegahan Kecelakaan Pesan Utama 6", 
  "description": "Pencegahan Kecelakaan Pesan Utama 6", 
  "language": "ind_ID", 
  "title": "Pencegahan Kecelakaan Pesan Utama 6", 
  "primary_category": "e76f1e313b9840d689be5f2ea157245b", 
  "created_at": "2015-01-08T04:46:48.927304+00:00", 
  "featured_in_category": false, 
  "modified_at": "2015-01-08T04:46:48.927486+00:00", 
  "_version": {
    "package_version": "0.3.1", 
    "language_version": "2.7.6", 
    "language_version_string": "2.7.6 (default, Mar 22 2014, 23:03:41) \n[GCC 4.8.2]", 
    "language": "python", 
    "package": "elastic-git"
  }, 
  "linked_pages": [], 
  "id": null, 
  "content": "**Pencegahan Kecelakaan Pesan Utama 6**\r\n\r\n6. Racun, obat-obatan, pemutih, cairan kimia dan cairan pembakar seperti\r\nparafin atau kerosin tidak boleh disimpan dalam botol minuman. Semua\r\ncairan dan racun harus disimpan dengan tanda yang jelas dan jauh dari\r\npenglihatan dan jangkauan anak.\r\n\r\n**Informasi Pendukung**\r\n\r\nKeracunan sangat berbahaya untuk anak-anak. Cairan pemutih, racun serangga dan racun\r\ntikus, parafin, kerosin, dan deterjen dapat mematikan atau mencelakakan anak.\r\nBanyak racun yang membahayakan walaupun tidak tertelan. Racun-racun tersebut menyebabkan\r\n\r\n**kerusakan otak, buta, atau cacat, jika :**\r\n\r\n1. Dihirup, tertelan\r\n2. Terkena kulit anak atau masuk ke mata\r\n3. Masuk ke baju anak\r\n\r\nRacun yang disimpan dalam botol minuman, gelas, atau mangkok dapat terminum oleh anak\r\ntanpa sengaja. Semua obat, bahan kimia dan racun harus disimpan dalam tempatnya yang asli\r\n(botol, kaleng, dll) dan ditutup rapat. Deterjen, pemutih, cairan kimia, dan obat-obatan jangan\r\nsampai dijangkau anak. Bahan-bahan itu harus ditutup rapat dan diberi tanda, disimpan di\r\nlemari terkunci atau rak yang tinggi sehingga tak terjangkau oleh anak.\r\n\r\nObat-obatan untuk orang dewasa dapat membunuh anak kecil. Obat hanya diberikan kepada\r\nanak kalau resepnya memang untuk anak yang bersangkutan, jangan memberikan obat orang\r\ndewasa atau milik anak yang lain.\r\n\r\nSalah pakai atau terlalu banyak antibiotik dapat menyebabkan tuli pada anak. Aspirin sering\r\nmenyebabkan keracunan pada anak.", 
  "source": null, 
  "featured": false, 
  "author_tags": [], 
  "image": null, 
  "published": null, 
  "position": 0, 
  "image_host": "http://thumbor.unicore.io", 
  "slug": "pencegahan-kecelakaan-pesan-utama-6", 
  "uuid": "e338848cdf284518af85923c8fed4f0d"
}