{
  "subtitle": "Malaria Pesan Utama 5", 
  "description": "Malaria Pesan Utama 5\r\n", 
  "language": "ind_ID", 
  "title": "Malaria Pesan Utama 5", 
  "primary_category": "49f1a5d9b2f8478e82f2224bb178f7cd", 
  "created_at": "2015-01-06T07:22:42+00:00", 
  "featured_in_category": false, 
  "modified_at": "2016-10-04T10:50:44.890373+00:00", 
  "_version": {
    "package_version": "0.3.1", 
    "language_version": "2.7.6", 
    "language": "python", 
    "language_version_string": "2.7.6 (default, Mar 22 2014, 23:03:41) \n[GCC 4.8.2]", 
    "package": "elastic-git"
  }, 
  "linked_pages": [], 
  "id": null, 
  "content": "**Malaria Pesan Utama 5**\r\n\r\n5.Keluarga dan masyarakat dapat mencegah malaria dengan menjaga\r\nkebersihan lingkungan untuk menghentikan perkembangan nyamuk.\r\n\r\n**Informasi Pendukung**\r\n\r\nKita menyadari bahwa masalah malaria merupakan masalah kita bersama. Untuk mengatasi\r\nmasalah tersebut diperlukan kerjasama yang baik antara pemerintah dan masyarakat. Keluarga dan\r\nmasyarakat dapat mencegah malaria dengan menjaga kebersihan lingkungan untuk menghentikan\r\nperkembangan nyamuk.\r\n\r\nDalam menghentikan perkembangan nyamuk, setiap keluarga dapat melakukan kegiatan untuk\r\nmengurangi jumlah nyamuk malaria, seperti membersihkan rumput, semak-semak di tepi saluran\r\ndan sekitar rumah, melipat kain-kain yang bergantungan di dalam ruangan (rumah), mengusahakan\r\nkeadaaan di dalam rumah tidak ada tempat-tempat yang gelap dan lembab, mengalirkan genangangenangan\r\nair dalam rumahnya, mengeringkan air yang tergenang dan membunuh jentik-jentik\r\ndengan menebarkan ikan pemakan jentik dan pemberian larvisida.\r\n", 
  "source": null, 
  "featured": false, 
  "author_tags": [], 
  "image": null, 
  "published": null, 
  "position": 5, 
  "image_host": "http://thumbor.unicore.io", 
  "slug": "malaria-pesan-utama-5", 
  "uuid": "e517819413964354a4c6dba72a17d1a5"
}